CHANGES.md
LICENSE
MANIFEST.in
README.md
setup.py
docs/Makefile
docs/conf.py
docs/_static/custom.css
docs/_templates/layout.html
pyppeteer/__init__.py
pyppeteer/browser.py
pyppeteer/chromium_downloader.py
pyppeteer/command.py
pyppeteer/connection.py
pyppeteer/coverage.py
pyppeteer/dialog.py
pyppeteer/element_handle.py
pyppeteer/emulation_manager.py
pyppeteer/errors.py
pyppeteer/execution_context.py
pyppeteer/frame_manager.py
pyppeteer/helper.py
pyppeteer/input.py
pyppeteer/launcher.py
pyppeteer/multimap.py
pyppeteer/navigator_watcher.py
pyppeteer/network_manager.py
pyppeteer/options.py
pyppeteer/page.py
pyppeteer/target.py
pyppeteer/tracing.py
pyppeteer/us_keyboard_layout.py
pyppeteer/util.py
pyppeteer/worker.py
pyppeteer_box.egg-info/PKG-INFO
pyppeteer_box.egg-info/SOURCES.txt
pyppeteer_box.egg-info/dependency_links.txt
pyppeteer_box.egg-info/entry_points.txt
pyppeteer_box.egg-info/not-zip-safe
pyppeteer_box.egg-info/requires.txt
pyppeteer_box.egg-info/top_level.txt
tests/__init__.py
tests/base.py
tests/blank_800x600.png
tests/closeme.py
tests/dumpio.py
tests/file-to-upload.txt
tests/frame_utils.py
tests/server.py
tests/test_abnormal_crash.py
tests/test_browser.py
tests/test_browser_context.py
tests/test_connection.py
tests/test_coverage.py
tests/test_dialog.py
tests/test_element_handle.py
tests/test_execution_context.py
tests/test_frame.py
tests/test_input.py
tests/test_launcher.py
tests/test_misc.py
tests/test_network.py
tests/test_page.py
tests/test_pyppeteer.py
tests/test_screenshot.py
tests/test_target.py
tests/test_tracing.py
tests/test_worker.py
tests/utils.py
tests/static/beforeunload.html
tests/static/button.html
tests/static/checkbox.html
tests/static/csp.html
tests/static/detect-touch.html
tests/static/error.html
tests/static/fileupload.html
tests/static/frame-204.html
tests/static/frame.html
tests/static/grid.html
tests/static/historyapi.html
tests/static/huge-image.png
tests/static/huge-page.html
tests/static/injectedfile.js
tests/static/injectedstyle.css
tests/static/keyboard.html
tests/static/mobile.html
tests/static/modernizr.js
tests/static/mouse-helper.js
tests/static/nested-frames.html
tests/static/offscreenbuttons.html
tests/static/one-frame.html
tests/static/one-style.css
