Metadata-Version: 2.1
Name: pyppeteer-box
Version: 0.0.27
Summary: Headless chrome/chromium automation library (unofficial port of puppeteer)
Home-page: https://github.com/pjialin/pyppeteer
Author: Hiroyuki Takagi
Author-email: miyako.dev@gmail.com
License: MIT license
Keywords: pyppeteer
Platform: UNKNOWN
Classifier: Development Status :: 3 - Alpha
Classifier: Intended Audience :: Developers
Classifier: License :: OSI Approved :: MIT License
Classifier: Natural Language :: English
Classifier: Programming Language :: Python :: 3
Classifier: Programming Language :: Python :: 3.5
Classifier: Programming Language :: Python :: 3.6
Classifier: Programming Language :: Python :: 3.7
Requires-Python: >=3.5
